package com.google.android.gms.internal;

import android.os.Binder;
import android.os.IBinder;
import android.os.IInterface;
import android.os.Parcel;
import android.os.ParcelFileDescriptor;
import android.os.Parcelable.Creator;
import android.os.RemoteException;
import com.google.android.gms.appdatasearch.GetRecentContextCall.Response;
import com.google.android.gms.appdatasearch.zzg;
import com.google.android.gms.common.api.Status;

public abstract interface zzjd
  extends IInterface
{
  public abstract void zza(GetRecentContextCall.Response paramResponse)
    throws RemoteException;
  
  public abstract void zza(Status paramStatus, ParcelFileDescriptor paramParcelFileDescriptor)
    throws RemoteException;
  
  public abstract void zza(Status paramStatus, boolean paramBoolean)
    throws RemoteException;
  
  public abstract void zzc(Status paramStatus)
    throws RemoteException;
  
  public static abstract class zza
    extends Binder
    implements zzjd
  {
    public zza()
    {
      attachInterface(this, "com.google.android.gms.appdatasearch.internal.ILightweightAppDataSearchCallbacks");
    }
    
    public static zzjd zzag(IBinder paramIBinder)
    {
      if (paramIBinder == null) {
        return null;
      }
      IInterface localIInterface = paramIBinder.queryLocalInterface("com.google.android.gms.appdatasearch.internal.ILightweightAppDataSearchCallbacks");
      if ((localIInterface != null) && ((localIInterface instanceof zzjd))) {
        return (zzjd)localIInterface;
      }
      return new zza(paramIBinder);
    }
    
    public IBinder asBinder()
    {
      return this;
    }
    
    public boolean onTransact(int paramInt1, Parcel paramParcel1, Parcel paramParcel2, int paramInt2)
      throws RemoteException
    {
      Object localObject = null;
      switch (paramInt1)
      {
      default: 
        return super.onTransact(paramInt1, paramParcel1, paramParcel2, paramInt2);
      case 1598968902: 
        paramParcel2.writeString("com.google.android.gms.appdatasearch.internal.ILightweightAppDataSearchCallbacks");
        return true;
      case 1: 
        paramParcel1.enforceInterface("com.google.android.gms.appdatasearch.internal.ILightweightAppDataSearchCallbacks");
        if (paramParcel1.readInt() != 0) {}
        for (paramParcel1 = (Status)Status.CREATOR.createFromParcel(paramParcel1);; paramParcel1 = null)
        {
          zzc(paramParcel1);
          return true;
        }
      case 2: 
        paramParcel1.enforceInterface("com.google.android.gms.appdatasearch.internal.ILightweightAppDataSearchCallbacks");
        if (paramParcel1.readInt() != 0)
        {
          paramParcel2 = (Status)Status.CREATOR.createFromParcel(paramParcel1);
          if (paramParcel1.readInt() == 0) {
            break label171;
          }
        }
        for (paramParcel1 = (ParcelFileDescriptor)ParcelFileDescriptor.CREATOR.createFromParcel(paramParcel1);; paramParcel1 = null)
        {
          zza(paramParcel2, paramParcel1);
          return true;
          paramParcel2 = null;
          break;
        }
      case 3: 
        label171:
        paramParcel1.enforceInterface("com.google.android.gms.appdatasearch.internal.ILightweightAppDataSearchCallbacks");
        if (paramParcel1.readInt() != 0)
        {
          paramParcel2 = (Status)Status.CREATOR.createFromParcel(paramParcel1);
          if (paramParcel1.readInt() == 0) {
            break label226;
          }
        }
        label226:
        for (boolean bool = true;; bool = false)
        {
          zza(paramParcel2, bool);
          return true;
          paramParcel2 = null;
          break;
        }
      }
      paramParcel1.enforceInterface("com.google.android.gms.appdatasearch.internal.ILightweightAppDataSearchCallbacks");
      paramParcel2 = localObject;
      if (paramParcel1.readInt() != 0) {
        paramParcel2 = GetRecentContextCall.Response.CREATOR.zzx(paramParcel1);
      }
      zza(paramParcel2);
      return true;
    }
    
    private static class zza
      implements zzjd
    {
      private IBinder zznI;
      
      zza(IBinder paramIBinder)
      {
        zznI = paramIBinder;
      }
      
      public IBinder asBinder()
      {
        return zznI;
      }
      
      /* Error */
      public void zza(GetRecentContextCall.Response paramResponse)
        throws RemoteException
      {
        // Byte code:
        //   0: invokestatic 30	android/os/Parcel:obtain	()Landroid/os/Parcel;
        //   3: astore_2
        //   4: aload_2
        //   5: ldc 32
        //   7: invokevirtual 36	android/os/Parcel:writeInterfaceToken	(Ljava/lang/String;)V
        //   10: aload_1
        //   11: ifnull +33 -> 44
        //   14: aload_2
        //   15: iconst_1
        //   16: invokevirtual 40	android/os/Parcel:writeInt	(I)V
        //   19: aload_1
        //   20: aload_2
        //   21: iconst_0
        //   22: invokevirtual 46	com/google/android/gms/appdatasearch/GetRecentContextCall$Response:writeToParcel	(Landroid/os/Parcel;I)V
        //   25: aload_0
        //   26: getfield 18	com/google/android/gms/internal/zzjd$zza$zza:zznI	Landroid/os/IBinder;
        //   29: iconst_4
        //   30: aload_2
        //   31: aconst_null
        //   32: iconst_1
        //   33: invokeinterface 52 5 0
        //   38: pop
        //   39: aload_2
        //   40: invokevirtual 55	android/os/Parcel:recycle	()V
        //   43: return
        //   44: aload_2
        //   45: iconst_0
        //   46: invokevirtual 40	android/os/Parcel:writeInt	(I)V
        //   49: goto -24 -> 25
        //   52: astore_1
        //   53: aload_2
        //   54: invokevirtual 55	android/os/Parcel:recycle	()V
        //   57: aload_1
        //   58: athrow
        // Local variable table:
        //   start	length	slot	name	signature
        //   0	59	0	this	zza
        //   0	59	1	paramResponse	GetRecentContextCall.Response
        //   3	51	2	localParcel	Parcel
        // Exception table:
        //   from	to	target	type
        //   4	10	52	finally
        //   14	25	52	finally
        //   25	39	52	finally
        //   44	49	52	finally
      }
      
      public void zza(Status paramStatus, ParcelFileDescriptor paramParcelFileDescriptor)
        throws RemoteException
      {
        Parcel localParcel = Parcel.obtain();
        for (;;)
        {
          try
          {
            localParcel.writeInterfaceToken("com.google.android.gms.appdatasearch.internal.ILightweightAppDataSearchCallbacks");
            if (paramStatus != null)
            {
              localParcel.writeInt(1);
              paramStatus.writeToParcel(localParcel, 0);
              if (paramParcelFileDescriptor != null)
              {
                localParcel.writeInt(1);
                paramParcelFileDescriptor.writeToParcel(localParcel, 0);
                zznI.transact(2, localParcel, null, 1);
              }
            }
            else
            {
              localParcel.writeInt(0);
              continue;
            }
            localParcel.writeInt(0);
          }
          finally
          {
            localParcel.recycle();
          }
        }
      }
      
      public void zza(Status paramStatus, boolean paramBoolean)
        throws RemoteException
      {
        int i = 1;
        Parcel localParcel = Parcel.obtain();
        for (;;)
        {
          try
          {
            localParcel.writeInterfaceToken("com.google.android.gms.appdatasearch.internal.ILightweightAppDataSearchCallbacks");
            if (paramStatus != null)
            {
              localParcel.writeInt(1);
              paramStatus.writeToParcel(localParcel, 0);
              break label83;
              localParcel.writeInt(i);
              zznI.transact(3, localParcel, null, 1);
            }
            else
            {
              localParcel.writeInt(0);
            }
          }
          finally
          {
            localParcel.recycle();
          }
          label83:
          do
          {
            i = 0;
            break;
          } while (!paramBoolean);
        }
      }
      
      /* Error */
      public void zzc(Status paramStatus)
        throws RemoteException
      {
        // Byte code:
        //   0: invokestatic 30	android/os/Parcel:obtain	()Landroid/os/Parcel;
        //   3: astore_2
        //   4: aload_2
        //   5: ldc 32
        //   7: invokevirtual 36	android/os/Parcel:writeInterfaceToken	(Ljava/lang/String;)V
        //   10: aload_1
        //   11: ifnull +33 -> 44
        //   14: aload_2
        //   15: iconst_1
        //   16: invokevirtual 40	android/os/Parcel:writeInt	(I)V
        //   19: aload_1
        //   20: aload_2
        //   21: iconst_0
        //   22: invokevirtual 60	com/google/android/gms/common/api/Status:writeToParcel	(Landroid/os/Parcel;I)V
        //   25: aload_0
        //   26: getfield 18	com/google/android/gms/internal/zzjd$zza$zza:zznI	Landroid/os/IBinder;
        //   29: iconst_1
        //   30: aload_2
        //   31: aconst_null
        //   32: iconst_1
        //   33: invokeinterface 52 5 0
        //   38: pop
        //   39: aload_2
        //   40: invokevirtual 55	android/os/Parcel:recycle	()V
        //   43: return
        //   44: aload_2
        //   45: iconst_0
        //   46: invokevirtual 40	android/os/Parcel:writeInt	(I)V
        //   49: goto -24 -> 25
        //   52: astore_1
        //   53: aload_2
        //   54: invokevirtual 55	android/os/Parcel:recycle	()V
        //   57: aload_1
        //   58: athrow
        // Local variable table:
        //   start	length	slot	name	signature
        //   0	59	0	this	zza
        //   0	59	1	paramStatus	Status
        //   3	51	2	localParcel	Parcel
        // Exception table:
        //   from	to	target	type
        //   4	10	52	finally
        //   14	25	52	finally
        //   25	39	52	finally
        //   44	49	52	finally
      }
    }
  }
}
