package com.google.android.gms.internal;

import android.content.Context;
import android.util.DisplayMetrics;
import android.view.MotionEvent;
import dalvik.system.DexClassLoader;
import java.io.File;
import java.io.FileNotFoundException;
import java.io.FileOutputStream;
import java.io.IOException;
import java.io.UnsupportedEncodingException;
import java.lang.reflect.InvocationTargetException;
import java.lang.reflect.Method;
import java.nio.ByteBuffer;
import java.util.ArrayList;

public abstract class zzal
  extends zzak
{
  private static long startTime = 0L;
  private static Method zzmY;
  private static Method zzmZ;
  private static Method zzna;
  private static Method zznb;
  private static Method zznc;
  private static Method zznd;
  private static Method zzne;
  private static Method zznf;
  private static Method zzng;
  private static Method zznh;
  private static Method zzni;
  private static Method zznj;
  private static Method zznk;
  private static String zznl;
  private static String zznm;
  private static String zznn;
  private static zzar zzno;
  static boolean zznp = false;
  
  protected zzal(Context paramContext, zzap paramZzap, zzaq paramZzaq)
  {
    super(paramContext, paramZzap, paramZzaq);
  }
  
  static String zzU()
    throws zzal.zza
  {
    if (zznl == null) {
      throw new zza();
    }
    return zznl;
  }
  
  static Long zzV()
    throws zzal.zza
  {
    if (zzmY == null) {
      throw new zza();
    }
    try
    {
      Long localLong = (Long)zzmY.invoke(null, new Object[0]);
      return localLong;
    }
    catch (IllegalAccessException localIllegalAccessException)
    {
      throw new zza(localIllegalAccessException);
    }
    catch (InvocationTargetException localInvocationTargetException)
    {
      throw new zza(localInvocationTargetException);
    }
  }
  
  static String zzW()
    throws zzal.zza
  {
    if (zzna == null) {
      throw new zza();
    }
    try
    {
      String str = (String)zzna.invoke(null, new Object[0]);
      return str;
    }
    catch (IllegalAccessException localIllegalAccessException)
    {
      throw new zza(localIllegalAccessException);
    }
    catch (InvocationTargetException localInvocationTargetException)
    {
      throw new zza(localInvocationTargetException);
    }
  }
  
  static Long zzX()
    throws zzal.zza
  {
    if (zzmZ == null) {
      throw new zza();
    }
    try
    {
      Long localLong = (Long)zzmZ.invoke(null, new Object[0]);
      return localLong;
    }
    catch (IllegalAccessException localIllegalAccessException)
    {
      throw new zza(localIllegalAccessException);
    }
    catch (InvocationTargetException localInvocationTargetException)
    {
      throw new zza(localInvocationTargetException);
    }
  }
  
  static String zza(Context paramContext, zzap paramZzap)
    throws zzal.zza
  {
    if (zznm != null) {
      return zznm;
    }
    if (zznb == null) {
      throw new zza();
    }
    try
    {
      paramContext = (ByteBuffer)zznb.invoke(null, new Object[] { paramContext });
      if (paramContext == null) {
        throw new zza();
      }
    }
    catch (IllegalAccessException paramContext)
    {
      throw new zza(paramContext);
      zznm = paramZzap.zza(paramContext.array(), true);
      paramContext = zznm;
      return paramContext;
    }
    catch (InvocationTargetException paramContext)
    {
      throw new zza(paramContext);
    }
  }
  
  static ArrayList<Long> zza(MotionEvent paramMotionEvent, DisplayMetrics paramDisplayMetrics)
    throws zzal.zza
  {
    if ((zznc == null) || (paramMotionEvent == null)) {
      throw new zza();
    }
    try
    {
      paramMotionEvent = (ArrayList)zznc.invoke(null, new Object[] { paramMotionEvent, paramDisplayMetrics });
      return paramMotionEvent;
    }
    catch (IllegalAccessException paramMotionEvent)
    {
      throw new zza(paramMotionEvent);
    }
    catch (InvocationTargetException paramMotionEvent)
    {
      throw new zza(paramMotionEvent);
    }
  }
  
  /* Error */
  protected static void zza(String paramString, Context paramContext, zzap paramZzap)
  {
    // Byte code:
    //   0: ldc 2
    //   2: monitorenter
    //   3: getstatic 37	com/google/android/gms/internal/zzal:zznp	Z
    //   6: istore_3
    //   7: iload_3
    //   8: ifne +36 -> 44
    //   11: new 106	com/google/android/gms/internal/zzar
    //   14: dup
    //   15: aload_2
    //   16: aconst_null
    //   17: invokespecial 109	com/google/android/gms/internal/zzar:<init>	(Lcom/google/android/gms/internal/zzap;Ljava/security/SecureRandom;)V
    //   20: putstatic 111	com/google/android/gms/internal/zzal:zzno	Lcom/google/android/gms/internal/zzar;
    //   23: aload_0
    //   24: putstatic 46	com/google/android/gms/internal/zzal:zznl	Ljava/lang/String;
    //   27: aload_1
    //   28: invokestatic 115	com/google/android/gms/internal/zzal:zzl	(Landroid/content/Context;)V
    //   31: invokestatic 117	com/google/android/gms/internal/zzal:zzV	()Ljava/lang/Long;
    //   34: invokevirtual 121	java/lang/Long:longValue	()J
    //   37: putstatic 35	com/google/android/gms/internal/zzal:startTime	J
    //   40: iconst_1
    //   41: putstatic 37	com/google/android/gms/internal/zzal:zznp	Z
    //   44: ldc 2
    //   46: monitorexit
    //   47: return
    //   48: astore_0
    //   49: ldc 2
    //   51: monitorexit
    //   52: aload_0
    //   53: athrow
    //   54: astore_0
    //   55: goto -11 -> 44
    //   58: astore_0
    //   59: goto -15 -> 44
    // Local variable table:
    //   start	length	slot	name	signature
    //   0	62	0	paramString	String
    //   0	62	1	paramContext	Context
    //   0	62	2	paramZzap	zzap
    //   6	2	3	bool	boolean
    // Exception table:
    //   from	to	target	type
    //   3	7	48	finally
    //   11	44	48	finally
    //   11	44	54	java/lang/UnsupportedOperationException
    //   11	44	58	com/google/android/gms/internal/zzal$zza
  }
  
  static String zzb(Context paramContext, zzap paramZzap)
    throws zzal.zza
  {
    if (zznn != null) {
      return zznn;
    }
    if (zzne == null) {
      throw new zza();
    }
    try
    {
      paramContext = (ByteBuffer)zzne.invoke(null, new Object[] { paramContext });
      if (paramContext == null) {
        throw new zza();
      }
    }
    catch (IllegalAccessException paramContext)
    {
      throw new zza(paramContext);
      zznn = paramZzap.zza(paramContext.array(), true);
      paramContext = zznn;
      return paramContext;
    }
    catch (InvocationTargetException paramContext)
    {
      throw new zza(paramContext);
    }
  }
  
  private static String zzb(byte[] paramArrayOfByte, String paramString)
    throws zzal.zza
  {
    try
    {
      paramArrayOfByte = new String(zzno.zzc(paramArrayOfByte, paramString), "UTF-8");
      return paramArrayOfByte;
    }
    catch (zzar.zza paramArrayOfByte)
    {
      throw new zza(paramArrayOfByte);
    }
    catch (UnsupportedEncodingException paramArrayOfByte)
    {
      throw new zza(paramArrayOfByte);
    }
  }
  
  static String zze(Context paramContext)
    throws zzal.zza
  {
    if (zznd == null) {
      throw new zza();
    }
    try
    {
      paramContext = (String)zznd.invoke(null, new Object[] { paramContext });
      if (paramContext == null) {
        throw new zza();
      }
    }
    catch (IllegalAccessException paramContext)
    {
      throw new zza(paramContext);
    }
    catch (InvocationTargetException paramContext)
    {
      throw new zza(paramContext);
    }
    return paramContext;
  }
  
  static String zzf(Context paramContext)
    throws zzal.zza
  {
    if (zznh == null) {
      throw new zza();
    }
    try
    {
      paramContext = (String)zznh.invoke(null, new Object[] { paramContext });
      return paramContext;
    }
    catch (IllegalAccessException paramContext)
    {
      throw new zza(paramContext);
    }
    catch (InvocationTargetException paramContext)
    {
      throw new zza(paramContext);
    }
  }
  
  static Long zzg(Context paramContext)
    throws zzal.zza
  {
    if (zzni == null) {
      throw new zza();
    }
    try
    {
      paramContext = (Long)zzni.invoke(null, new Object[] { paramContext });
      return paramContext;
    }
    catch (IllegalAccessException paramContext)
    {
      throw new zza(paramContext);
    }
    catch (InvocationTargetException paramContext)
    {
      throw new zza(paramContext);
    }
  }
  
  static ArrayList<Long> zzh(Context paramContext)
    throws zzal.zza
  {
    if (zznf == null) {
      throw new zza();
    }
    try
    {
      paramContext = (ArrayList)zznf.invoke(null, new Object[] { paramContext });
      if ((paramContext == null) || (paramContext.size() != 2)) {
        throw new zza();
      }
    }
    catch (IllegalAccessException paramContext)
    {
      throw new zza(paramContext);
    }
    catch (InvocationTargetException paramContext)
    {
      throw new zza(paramContext);
    }
    return paramContext;
  }
  
  static int[] zzi(Context paramContext)
    throws zzal.zza
  {
    if (zzng == null) {
      throw new zza();
    }
    try
    {
      paramContext = (int[])zzng.invoke(null, new Object[] { paramContext });
      return paramContext;
    }
    catch (IllegalAccessException paramContext)
    {
      throw new zza(paramContext);
    }
    catch (InvocationTargetException paramContext)
    {
      throw new zza(paramContext);
    }
  }
  
  static int zzj(Context paramContext)
    throws zzal.zza
  {
    if (zznj == null) {
      throw new zza();
    }
    try
    {
      int i = ((Integer)zznj.invoke(null, new Object[] { paramContext })).intValue();
      return i;
    }
    catch (IllegalAccessException paramContext)
    {
      throw new zza(paramContext);
    }
    catch (InvocationTargetException paramContext)
    {
      throw new zza(paramContext);
    }
  }
  
  static int zzk(Context paramContext)
    throws zzal.zza
  {
    if (zznk == null) {
      throw new zza();
    }
    try
    {
      int i = ((Integer)zznk.invoke(null, new Object[] { paramContext })).intValue();
      return i;
    }
    catch (IllegalAccessException paramContext)
    {
      throw new zza(paramContext);
    }
    catch (InvocationTargetException paramContext)
    {
      throw new zza(paramContext);
    }
  }
  
  private static void zzl(Context paramContext)
    throws zzal.zza
  {
    try
    {
      localObject1 = zzno.zzl(zzat.getKey());
      localObject2 = zzno.zzc((byte[])localObject1, zzat.zzad());
      localFile2 = paramContext.getCacheDir();
      localFile1 = localFile2;
      if (localFile2 == null)
      {
        localFile2 = paramContext.getDir("dex", 0);
        localFile1 = localFile2;
        if (localFile2 == null) {
          throw new zza();
        }
      }
    }
    catch (FileNotFoundException paramContext)
    {
      Object localObject1;
      Object localObject2;
      File localFile1;
      throw new zza(paramContext);
      File localFile2 = File.createTempFile("ads", ".jar", localFile1);
      Object localObject3 = new FileOutputStream(localFile2);
      ((FileOutputStream)localObject3).write((byte[])localObject2, 0, localObject2.length);
      ((FileOutputStream)localObject3).close();
      try
      {
        Object localObject4 = new DexClassLoader(localFile2.getAbsolutePath(), localFile1.getAbsolutePath(), null, paramContext.getClassLoader());
        paramContext = ((DexClassLoader)localObject4).loadClass(zzb((byte[])localObject1, zzat.zzam()));
        localObject2 = ((DexClassLoader)localObject4).loadClass(zzb((byte[])localObject1, zzat.zzaA()));
        localObject3 = ((DexClassLoader)localObject4).loadClass(zzb((byte[])localObject1, zzat.zzau()));
        Class localClass1 = ((DexClassLoader)localObject4).loadClass(zzb((byte[])localObject1, zzat.zzaq()));
        Class localClass2 = ((DexClassLoader)localObject4).loadClass(zzb((byte[])localObject1, zzat.zzaC()));
        Class localClass3 = ((DexClassLoader)localObject4).loadClass(zzb((byte[])localObject1, zzat.zzao()));
        Class localClass4 = ((DexClassLoader)localObject4).loadClass(zzb((byte[])localObject1, zzat.zzay()));
        Class localClass5 = ((DexClassLoader)localObject4).loadClass(zzb((byte[])localObject1, zzat.zzaw()));
        Class localClass6 = ((DexClassLoader)localObject4).loadClass(zzb((byte[])localObject1, zzat.zzak()));
        Class localClass7 = ((DexClassLoader)localObject4).loadClass(zzb((byte[])localObject1, zzat.zzai()));
        Class localClass8 = ((DexClassLoader)localObject4).loadClass(zzb((byte[])localObject1, zzat.zzag()));
        Class localClass9 = ((DexClassLoader)localObject4).loadClass(zzb((byte[])localObject1, zzat.zzas()));
        localObject4 = ((DexClassLoader)localObject4).loadClass(zzb((byte[])localObject1, zzat.zzae()));
        zzmY = paramContext.getMethod(zzb((byte[])localObject1, zzat.zzan()), new Class[0]);
        zzmZ = ((Class)localObject2).getMethod(zzb((byte[])localObject1, zzat.zzaB()), new Class[0]);
        zzna = ((Class)localObject3).getMethod(zzb((byte[])localObject1, zzat.zzav()), new Class[0]);
        zznb = localClass1.getMethod(zzb((byte[])localObject1, zzat.zzar()), new Class[] { Context.class });
        zznc = localClass2.getMethod(zzb((byte[])localObject1, zzat.zzaD()), new Class[] { MotionEvent.class, DisplayMetrics.class });
        zznd = localClass3.getMethod(zzb((byte[])localObject1, zzat.zzap()), new Class[] { Context.class });
        zzne = localClass4.getMethod(zzb((byte[])localObject1, zzat.zzaz()), new Class[] { Context.class });
        zznf = localClass5.getMethod(zzb((byte[])localObject1, zzat.zzax()), new Class[] { Context.class });
        zzng = localClass6.getMethod(zzb((byte[])localObject1, zzat.zzal()), new Class[] { Context.class });
        zznh = localClass7.getMethod(zzb((byte[])localObject1, zzat.zzaj()), new Class[] { Context.class });
        zzni = localClass8.getMethod(zzb((byte[])localObject1, zzat.zzah()), new Class[] { Context.class });
        zznj = localClass9.getMethod(zzb((byte[])localObject1, zzat.zzat()), new Class[] { Context.class });
        zznk = ((Class)localObject4).getMethod(zzb((byte[])localObject1, zzat.zzaf()), new Class[] { Context.class });
        return;
      }
      finally
      {
        localObject1 = localFile2.getName();
        localFile2.delete();
        new File(localFile1, ((String)localObject1).replace(".jar", ".dex")).delete();
      }
    }
    catch (IOException paramContext)
    {
      throw new zza(paramContext);
    }
    catch (ClassNotFoundException paramContext)
    {
      throw new zza(paramContext);
    }
    catch (zzar.zza paramContext)
    {
      throw new zza(paramContext);
    }
    catch (NoSuchMethodException paramContext)
    {
      throw new zza(paramContext);
    }
    catch (NullPointerException paramContext)
    {
      throw new zza(paramContext);
    }
  }
  
  /* Error */
  protected void zzc(Context paramContext)
  {
    // Byte code:
    //   0: aload_0
    //   1: iconst_1
    //   2: invokestatic 357	com/google/android/gms/internal/zzal:zzW	()Ljava/lang/String;
    //   5: invokevirtual 360	com/google/android/gms/internal/zzal:zza	(ILjava/lang/String;)V
    //   8: aload_0
    //   9: iconst_2
    //   10: invokestatic 362	com/google/android/gms/internal/zzal:zzU	()Ljava/lang/String;
    //   13: invokevirtual 360	com/google/android/gms/internal/zzal:zza	(ILjava/lang/String;)V
    //   16: invokestatic 117	com/google/android/gms/internal/zzal:zzV	()Ljava/lang/Long;
    //   19: invokevirtual 121	java/lang/Long:longValue	()J
    //   22: lstore_2
    //   23: aload_0
    //   24: bipush 25
    //   26: lload_2
    //   27: invokevirtual 365	com/google/android/gms/internal/zzal:zza	(IJ)V
    //   30: getstatic 35	com/google/android/gms/internal/zzal:startTime	J
    //   33: lconst_0
    //   34: lcmp
    //   35: ifeq +23 -> 58
    //   38: aload_0
    //   39: bipush 17
    //   41: lload_2
    //   42: getstatic 35	com/google/android/gms/internal/zzal:startTime	J
    //   45: lsub
    //   46: invokevirtual 365	com/google/android/gms/internal/zzal:zza	(IJ)V
    //   49: aload_0
    //   50: bipush 23
    //   52: getstatic 35	com/google/android/gms/internal/zzal:startTime	J
    //   55: invokevirtual 365	com/google/android/gms/internal/zzal:zza	(IJ)V
    //   58: aload_1
    //   59: invokestatic 367	com/google/android/gms/internal/zzal:zzh	(Landroid/content/Context;)Ljava/util/ArrayList;
    //   62: astore 4
    //   64: aload_0
    //   65: bipush 31
    //   67: aload 4
    //   69: iconst_0
    //   70: invokevirtual 371	java/util/ArrayList:get	(I)Ljava/lang/Object;
    //   73: checkcast 67	java/lang/Long
    //   76: invokevirtual 121	java/lang/Long:longValue	()J
    //   79: invokevirtual 365	com/google/android/gms/internal/zzal:zza	(IJ)V
    //   82: aload_0
    //   83: bipush 32
    //   85: aload 4
    //   87: iconst_1
    //   88: invokevirtual 371	java/util/ArrayList:get	(I)Ljava/lang/Object;
    //   91: checkcast 67	java/lang/Long
    //   94: invokevirtual 121	java/lang/Long:longValue	()J
    //   97: invokevirtual 365	com/google/android/gms/internal/zzal:zza	(IJ)V
    //   100: aload_0
    //   101: bipush 33
    //   103: invokestatic 373	com/google/android/gms/internal/zzal:zzX	()Ljava/lang/Long;
    //   106: invokevirtual 121	java/lang/Long:longValue	()J
    //   109: invokevirtual 365	com/google/android/gms/internal/zzal:zza	(IJ)V
    //   112: aload_0
    //   113: bipush 27
    //   115: aload_1
    //   116: aload_0
    //   117: getfield 377	com/google/android/gms/internal/zzal:zzmW	Lcom/google/android/gms/internal/zzap;
    //   120: invokestatic 379	com/google/android/gms/internal/zzal:zza	(Landroid/content/Context;Lcom/google/android/gms/internal/zzap;)Ljava/lang/String;
    //   123: invokevirtual 360	com/google/android/gms/internal/zzal:zza	(ILjava/lang/String;)V
    //   126: aload_0
    //   127: bipush 29
    //   129: aload_1
    //   130: aload_0
    //   131: getfield 377	com/google/android/gms/internal/zzal:zzmW	Lcom/google/android/gms/internal/zzap;
    //   134: invokestatic 381	com/google/android/gms/internal/zzal:zzb	(Landroid/content/Context;Lcom/google/android/gms/internal/zzap;)Ljava/lang/String;
    //   137: invokevirtual 360	com/google/android/gms/internal/zzal:zza	(ILjava/lang/String;)V
    //   140: aload_1
    //   141: invokestatic 383	com/google/android/gms/internal/zzal:zzi	(Landroid/content/Context;)[I
    //   144: astore 4
    //   146: aload_0
    //   147: iconst_5
    //   148: aload 4
    //   150: iconst_0
    //   151: iaload
    //   152: i2l
    //   153: invokevirtual 365	com/google/android/gms/internal/zzal:zza	(IJ)V
    //   156: aload_0
    //   157: bipush 6
    //   159: aload 4
    //   161: iconst_1
    //   162: iaload
    //   163: i2l
    //   164: invokevirtual 365	com/google/android/gms/internal/zzal:zza	(IJ)V
    //   167: aload_0
    //   168: bipush 12
    //   170: aload_1
    //   171: invokestatic 385	com/google/android/gms/internal/zzal:zzj	(Landroid/content/Context;)I
    //   174: i2l
    //   175: invokevirtual 365	com/google/android/gms/internal/zzal:zza	(IJ)V
    //   178: aload_0
    //   179: iconst_3
    //   180: aload_1
    //   181: invokestatic 387	com/google/android/gms/internal/zzal:zzk	(Landroid/content/Context;)I
    //   184: i2l
    //   185: invokevirtual 365	com/google/android/gms/internal/zzal:zza	(IJ)V
    //   188: aload_0
    //   189: bipush 34
    //   191: aload_1
    //   192: invokestatic 389	com/google/android/gms/internal/zzal:zzf	(Landroid/content/Context;)Ljava/lang/String;
    //   195: invokevirtual 360	com/google/android/gms/internal/zzal:zza	(ILjava/lang/String;)V
    //   198: aload_0
    //   199: bipush 35
    //   201: aload_1
    //   202: invokestatic 391	com/google/android/gms/internal/zzal:zzg	(Landroid/content/Context;)Ljava/lang/Long;
    //   205: invokevirtual 121	java/lang/Long:longValue	()J
    //   208: invokevirtual 365	com/google/android/gms/internal/zzal:zza	(IJ)V
    //   211: return
    //   212: astore_1
    //   213: return
    //   214: astore_1
    //   215: return
    //   216: astore 4
    //   218: goto -20 -> 198
    //   221: astore 4
    //   223: goto -35 -> 188
    //   226: astore 4
    //   228: goto -50 -> 178
    //   231: astore 4
    //   233: goto -66 -> 167
    //   236: astore 4
    //   238: goto -98 -> 140
    //   241: astore 4
    //   243: goto -117 -> 126
    //   246: astore 4
    //   248: goto -136 -> 112
    //   251: astore 4
    //   253: goto -153 -> 100
    //   256: astore 4
    //   258: goto -200 -> 58
    //   261: astore 4
    //   263: goto -247 -> 16
    //   266: astore 4
    //   268: goto -260 -> 8
    // Local variable table:
    //   start	length	slot	name	signature
    //   0	271	0	this	zzal
    //   0	271	1	paramContext	Context
    //   22	20	2	l	long
    //   62	98	4	localObject	Object
    //   216	1	4	localZza1	zza
    //   221	1	4	localZza2	zza
    //   226	1	4	localZza3	zza
    //   231	1	4	localZza4	zza
    //   236	1	4	localZza5	zza
    //   241	1	4	localZza6	zza
    //   246	1	4	localZza7	zza
    //   251	1	4	localZza8	zza
    //   256	1	4	localZza9	zza
    //   261	1	4	localZza10	zza
    //   266	1	4	localZza11	zza
    // Exception table:
    //   from	to	target	type
    //   0	8	212	java/io/IOException
    //   8	16	212	java/io/IOException
    //   16	58	212	java/io/IOException
    //   58	100	212	java/io/IOException
    //   100	112	212	java/io/IOException
    //   112	126	212	java/io/IOException
    //   126	140	212	java/io/IOException
    //   140	167	212	java/io/IOException
    //   167	178	212	java/io/IOException
    //   178	188	212	java/io/IOException
    //   188	198	212	java/io/IOException
    //   198	211	212	java/io/IOException
    //   198	211	214	com/google/android/gms/internal/zzal$zza
    //   188	198	216	com/google/android/gms/internal/zzal$zza
    //   178	188	221	com/google/android/gms/internal/zzal$zza
    //   167	178	226	com/google/android/gms/internal/zzal$zza
    //   140	167	231	com/google/android/gms/internal/zzal$zza
    //   126	140	236	com/google/android/gms/internal/zzal$zza
    //   112	126	241	com/google/android/gms/internal/zzal$zza
    //   100	112	246	com/google/android/gms/internal/zzal$zza
    //   58	100	251	com/google/android/gms/internal/zzal$zza
    //   16	58	256	com/google/android/gms/internal/zzal$zza
    //   8	16	261	com/google/android/gms/internal/zzal$zza
    //   0	8	266	com/google/android/gms/internal/zzal$zza
  }
  
  /* Error */
  protected void zzd(Context paramContext)
  {
    // Byte code:
    //   0: aload_0
    //   1: iconst_2
    //   2: invokestatic 362	com/google/android/gms/internal/zzal:zzU	()Ljava/lang/String;
    //   5: invokevirtual 360	com/google/android/gms/internal/zzal:zza	(ILjava/lang/String;)V
    //   8: aload_0
    //   9: iconst_1
    //   10: invokestatic 357	com/google/android/gms/internal/zzal:zzW	()Ljava/lang/String;
    //   13: invokevirtual 360	com/google/android/gms/internal/zzal:zza	(ILjava/lang/String;)V
    //   16: aload_0
    //   17: bipush 25
    //   19: invokestatic 117	com/google/android/gms/internal/zzal:zzV	()Ljava/lang/Long;
    //   22: invokevirtual 121	java/lang/Long:longValue	()J
    //   25: invokevirtual 365	com/google/android/gms/internal/zzal:zza	(IJ)V
    //   28: aload_0
    //   29: getfield 396	com/google/android/gms/internal/zzal:zzmU	Landroid/view/MotionEvent;
    //   32: aload_0
    //   33: getfield 400	com/google/android/gms/internal/zzal:zzmV	Landroid/util/DisplayMetrics;
    //   36: invokestatic 402	com/google/android/gms/internal/zzal:zza	(Landroid/view/MotionEvent;Landroid/util/DisplayMetrics;)Ljava/util/ArrayList;
    //   39: astore_2
    //   40: aload_0
    //   41: bipush 14
    //   43: aload_2
    //   44: iconst_0
    //   45: invokevirtual 371	java/util/ArrayList:get	(I)Ljava/lang/Object;
    //   48: checkcast 67	java/lang/Long
    //   51: invokevirtual 121	java/lang/Long:longValue	()J
    //   54: invokevirtual 365	com/google/android/gms/internal/zzal:zza	(IJ)V
    //   57: aload_0
    //   58: bipush 15
    //   60: aload_2
    //   61: iconst_1
    //   62: invokevirtual 371	java/util/ArrayList:get	(I)Ljava/lang/Object;
    //   65: checkcast 67	java/lang/Long
    //   68: invokevirtual 121	java/lang/Long:longValue	()J
    //   71: invokevirtual 365	com/google/android/gms/internal/zzal:zza	(IJ)V
    //   74: aload_2
    //   75: invokevirtual 159	java/util/ArrayList:size	()I
    //   78: iconst_3
    //   79: if_icmplt +20 -> 99
    //   82: aload_0
    //   83: bipush 16
    //   85: aload_2
    //   86: iconst_2
    //   87: invokevirtual 371	java/util/ArrayList:get	(I)Ljava/lang/Object;
    //   90: checkcast 67	java/lang/Long
    //   93: invokevirtual 121	java/lang/Long:longValue	()J
    //   96: invokevirtual 365	com/google/android/gms/internal/zzal:zza	(IJ)V
    //   99: aload_0
    //   100: bipush 34
    //   102: aload_1
    //   103: invokestatic 389	com/google/android/gms/internal/zzal:zzf	(Landroid/content/Context;)Ljava/lang/String;
    //   106: invokevirtual 360	com/google/android/gms/internal/zzal:zza	(ILjava/lang/String;)V
    //   109: aload_0
    //   110: bipush 35
    //   112: aload_1
    //   113: invokestatic 391	com/google/android/gms/internal/zzal:zzg	(Landroid/content/Context;)Ljava/lang/Long;
    //   116: invokevirtual 121	java/lang/Long:longValue	()J
    //   119: invokevirtual 365	com/google/android/gms/internal/zzal:zza	(IJ)V
    //   122: return
    //   123: astore_1
    //   124: return
    //   125: astore_1
    //   126: return
    //   127: astore_2
    //   128: goto -19 -> 109
    //   131: astore_2
    //   132: goto -33 -> 99
    //   135: astore_2
    //   136: goto -108 -> 28
    //   139: astore_2
    //   140: goto -124 -> 16
    //   143: astore_2
    //   144: goto -136 -> 8
    // Local variable table:
    //   start	length	slot	name	signature
    //   0	147	0	this	zzal
    //   0	147	1	paramContext	Context
    //   39	47	2	localArrayList	ArrayList
    //   127	1	2	localZza1	zza
    //   131	1	2	localZza2	zza
    //   135	1	2	localZza3	zza
    //   139	1	2	localZza4	zza
    //   143	1	2	localZza5	zza
    // Exception table:
    //   from	to	target	type
    //   0	8	123	java/io/IOException
    //   8	16	123	java/io/IOException
    //   16	28	123	java/io/IOException
    //   28	99	123	java/io/IOException
    //   99	109	123	java/io/IOException
    //   109	122	123	java/io/IOException
    //   109	122	125	com/google/android/gms/internal/zzal$zza
    //   99	109	127	com/google/android/gms/internal/zzal$zza
    //   28	99	131	com/google/android/gms/internal/zzal$zza
    //   16	28	135	com/google/android/gms/internal/zzal$zza
    //   8	16	139	com/google/android/gms/internal/zzal$zza
    //   0	8	143	com/google/android/gms/internal/zzal$zza
  }
  
  static class zza
    extends Exception
  {
    public zza() {}
    
    public zza(Throwable paramThrowable)
    {
      super();
    }
  }
}
