package com.google.android.gms.ads.internal.client;

import android.os.Binder;
import android.os.IBinder;
import android.os.IInterface;
import android.os.Parcel;
import android.os.RemoteException;

public abstract interface zzv
  extends IInterface
{
  public abstract void zza(String paramString, MobileAdsSettingsParcel paramMobileAdsSettingsParcel)
    throws RemoteException;
  
  public static abstract class zza
    extends Binder
    implements zzv
  {
    public zza()
    {
      attachInterface(this, "com.google.android.gms.ads.internal.client.IMobileAdsSettingManager");
    }
    
    public static zzv zzo(IBinder paramIBinder)
    {
      if (paramIBinder == null) {
        return null;
      }
      IInterface localIInterface = paramIBinder.queryLocalInterface("com.google.android.gms.ads.internal.client.IMobileAdsSettingManager");
      if ((localIInterface != null) && ((localIInterface instanceof zzv))) {
        return (zzv)localIInterface;
      }
      return new zza(paramIBinder);
    }
    
    public IBinder asBinder()
    {
      return this;
    }
    
    public boolean onTransact(int paramInt1, Parcel paramParcel1, Parcel paramParcel2, int paramInt2)
      throws RemoteException
    {
      switch (paramInt1)
      {
      default: 
        return super.onTransact(paramInt1, paramParcel1, paramParcel2, paramInt2);
      case 1598968902: 
        paramParcel2.writeString("com.google.android.gms.ads.internal.client.IMobileAdsSettingManager");
        return true;
      }
      paramParcel1.enforceInterface("com.google.android.gms.ads.internal.client.IMobileAdsSettingManager");
      String str = paramParcel1.readString();
      if (paramParcel1.readInt() != 0) {}
      for (paramParcel1 = MobileAdsSettingsParcel.CREATOR.zzd(paramParcel1);; paramParcel1 = null)
      {
        zza(str, paramParcel1);
        paramParcel2.writeNoException();
        return true;
      }
    }
    
    private static class zza
      implements zzv
    {
      private IBinder zznI;
      
      zza(IBinder paramIBinder)
      {
        zznI = paramIBinder;
      }
      
      public IBinder asBinder()
      {
        return zznI;
      }
      
      /* Error */
      public void zza(String paramString, MobileAdsSettingsParcel paramMobileAdsSettingsParcel)
        throws RemoteException
      {
        // Byte code:
        //   0: invokestatic 30	android/os/Parcel:obtain	()Landroid/os/Parcel;
        //   3: astore_3
        //   4: invokestatic 30	android/os/Parcel:obtain	()Landroid/os/Parcel;
        //   7: astore 4
        //   9: aload_3
        //   10: ldc 32
        //   12: invokevirtual 36	android/os/Parcel:writeInterfaceToken	(Ljava/lang/String;)V
        //   15: aload_3
        //   16: aload_1
        //   17: invokevirtual 39	android/os/Parcel:writeString	(Ljava/lang/String;)V
        //   20: aload_2
        //   21: ifnull +44 -> 65
        //   24: aload_3
        //   25: iconst_1
        //   26: invokevirtual 43	android/os/Parcel:writeInt	(I)V
        //   29: aload_2
        //   30: aload_3
        //   31: iconst_0
        //   32: invokevirtual 49	com/google/android/gms/ads/internal/client/MobileAdsSettingsParcel:writeToParcel	(Landroid/os/Parcel;I)V
        //   35: aload_0
        //   36: getfield 18	com/google/android/gms/ads/internal/client/zzv$zza$zza:zznI	Landroid/os/IBinder;
        //   39: iconst_1
        //   40: aload_3
        //   41: aload 4
        //   43: iconst_0
        //   44: invokeinterface 55 5 0
        //   49: pop
        //   50: aload 4
        //   52: invokevirtual 58	android/os/Parcel:readException	()V
        //   55: aload 4
        //   57: invokevirtual 61	android/os/Parcel:recycle	()V
        //   60: aload_3
        //   61: invokevirtual 61	android/os/Parcel:recycle	()V
        //   64: return
        //   65: aload_3
        //   66: iconst_0
        //   67: invokevirtual 43	android/os/Parcel:writeInt	(I)V
        //   70: goto -35 -> 35
        //   73: astore_1
        //   74: aload 4
        //   76: invokevirtual 61	android/os/Parcel:recycle	()V
        //   79: aload_3
        //   80: invokevirtual 61	android/os/Parcel:recycle	()V
        //   83: aload_1
        //   84: athrow
        // Local variable table:
        //   start	length	slot	name	signature
        //   0	85	0	this	zza
        //   0	85	1	paramString	String
        //   0	85	2	paramMobileAdsSettingsParcel	MobileAdsSettingsParcel
        //   3	77	3	localParcel1	Parcel
        //   7	68	4	localParcel2	Parcel
        // Exception table:
        //   from	to	target	type
        //   9	20	73	finally
        //   24	35	73	finally
        //   35	55	73	finally
        //   65	70	73	finally
      }
    }
  }
}
