import com.tencent.mobileqq.hotpatch.NotVerifyClass;

class men
  implements Runnable
{
  men(mek paramMek)
  {
    boolean bool = NotVerifyClass.DO_VERIFY_CLASS;
  }
  
  /* Error */
  public void run()
  {
    // Byte code:
    //   0: invokestatic 30	mek:a	()[B
    //   3: astore_3
    //   4: aload_3
    //   5: monitorenter
    //   6: aload_0
    //   7: getfield 12	men:a	Lmek;
    //   10: invokestatic 33	mek:a	(Lmek;)Ljava/util/Map;
    //   13: invokeinterface 39 1 0
    //   18: ifeq +9 -> 27
    //   21: invokestatic 30	mek:a	()[B
    //   24: invokevirtual 42	java/lang/Object:wait	()V
    //   27: invokestatic 30	mek:a	()[B
    //   30: ldc2_w 43
    //   33: invokevirtual 47	java/lang/Object:wait	(J)V
    //   36: aload_0
    //   37: getfield 12	men:a	Lmek;
    //   40: invokestatic 33	mek:a	(Lmek;)Ljava/util/Map;
    //   43: invokeinterface 51 1 0
    //   48: invokeinterface 57 1 0
    //   53: astore 4
    //   55: aload 4
    //   57: invokeinterface 62 1 0
    //   62: ifeq +173 -> 235
    //   65: aload 4
    //   67: invokeinterface 66 1 0
    //   72: checkcast 68	java/util/Map$Entry
    //   75: astore 5
    //   77: aload 5
    //   79: invokeinterface 71 1 0
    //   84: checkcast 73	java/lang/Long
    //   87: invokevirtual 77	java/lang/Long:longValue	()J
    //   90: lstore_1
    //   91: aload 5
    //   93: invokeinterface 80 1 0
    //   98: checkcast 82	VACDReport/ReportInfo
    //   101: astore 5
    //   103: aload 5
    //   105: ifnull -50 -> 55
    //   108: aload 5
    //   110: getfield 86	VACDReport/ReportInfo:body	LVACDReport/ReportBody;
    //   113: getfield 92	VACDReport/ReportBody:reportItems	Ljava/util/ArrayList;
    //   116: invokevirtual 95	java/util/ArrayList:isEmpty	()Z
    //   119: ifne -64 -> 55
    //   122: aload 5
    //   124: getfield 99	VACDReport/ReportInfo:header	LVACDReport/ReportHeader;
    //   127: ifnull +72 -> 199
    //   130: aload_0
    //   131: getfield 12	men:a	Lmek;
    //   134: invokestatic 102	mek:a	(Lmek;)Lmej;
    //   137: aload 5
    //   139: getfield 86	VACDReport/ReportInfo:body	LVACDReport/ReportBody;
    //   142: getfield 106	VACDReport/ReportBody:sKey	Ljava/lang/String;
    //   145: aload 5
    //   147: getfield 99	VACDReport/ReportInfo:header	LVACDReport/ReportHeader;
    //   150: invokevirtual 111	mej:a	(Ljava/lang/String;LVACDReport/ReportHeader;)V
    //   153: aload 5
    //   155: aconst_null
    //   156: putfield 99	VACDReport/ReportInfo:header	LVACDReport/ReportHeader;
    //   159: aload_0
    //   160: getfield 12	men:a	Lmek;
    //   163: invokestatic 102	mek:a	(Lmek;)Lmej;
    //   166: lload_1
    //   167: aload 5
    //   169: getfield 86	VACDReport/ReportInfo:body	LVACDReport/ReportBody;
    //   172: getfield 92	VACDReport/ReportBody:reportItems	Ljava/util/ArrayList;
    //   175: invokevirtual 114	mej:a	(JLjava/util/List;)V
    //   178: aload 5
    //   180: getfield 86	VACDReport/ReportInfo:body	LVACDReport/ReportBody;
    //   183: getfield 92	VACDReport/ReportBody:reportItems	Ljava/util/ArrayList;
    //   186: invokevirtual 117	java/util/ArrayList:clear	()V
    //   189: goto -134 -> 55
    //   192: astore 4
    //   194: aload_3
    //   195: monitorexit
    //   196: aload 4
    //   198: athrow
    //   199: aload 5
    //   201: getfield 86	VACDReport/ReportInfo:body	LVACDReport/ReportBody;
    //   204: getfield 106	VACDReport/ReportBody:sKey	Ljava/lang/String;
    //   207: invokestatic 122	android/text/TextUtils:isEmpty	(Ljava/lang/CharSequence;)Z
    //   210: ifne -51 -> 159
    //   213: aload_0
    //   214: getfield 12	men:a	Lmek;
    //   217: invokestatic 102	mek:a	(Lmek;)Lmej;
    //   220: lload_1
    //   221: aload 5
    //   223: getfield 86	VACDReport/ReportInfo:body	LVACDReport/ReportBody;
    //   226: getfield 106	VACDReport/ReportBody:sKey	Ljava/lang/String;
    //   229: invokevirtual 125	mej:a	(JLjava/lang/String;)V
    //   232: goto -73 -> 159
    //   235: aload_0
    //   236: getfield 12	men:a	Lmek;
    //   239: invokestatic 129	mek:b	(Lmek;)Landroid/os/Handler;
    //   242: aload_0
    //   243: invokevirtual 135	android/os/Handler:post	(Ljava/lang/Runnable;)Z
    //   246: pop
    //   247: aload_3
    //   248: monitorexit
    //   249: return
    //   250: astore 4
    //   252: goto -216 -> 36
    // Local variable table:
    //   start	length	slot	name	signature
    //   0	255	0	this	men
    //   90	131	1	l	long
    //   53	13	4	localIterator	java.util.Iterator
    //   192	5	4	localObject1	Object
    //   250	1	4	localInterruptedException	InterruptedException
    //   75	147	5	localObject2	Object
    // Exception table:
    //   from	to	target	type
    //   6	27	192	finally
    //   27	36	192	finally
    //   36	55	192	finally
    //   55	103	192	finally
    //   108	159	192	finally
    //   159	189	192	finally
    //   194	196	192	finally
    //   199	232	192	finally
    //   235	249	192	finally
    //   6	27	250	java/lang/InterruptedException
    //   27	36	250	java/lang/InterruptedException
  }
}
